AUTHORS.txt
CHANGELOG.txt
FAQ.txt
INSTALL.txt
LICENSE.txt
MANIFEST.in
NEWS.txt
README.txt
THANKS.txt
TODO.txt
VERSION.txt
setup.py
doc/Makefile
doc/caching.rst
doc/conf.py
doc/cookies.rst
doc/dispatch.rst
doc/getting_started.rst
doc/httputils.rst
doc/index.rst
doc/request.rst
doc/response.rst
doc/session.rst
doc/utils.rst
doc/wsgiutils.rst
pesto/__init__.py
pesto/caching.py
pesto/cookie.py
pesto/core.py
pesto/dispatch.py
pesto/httputils.py
pesto/request.py
pesto/response.py
pesto/testing.py
pesto/utils.py
pesto/wsgiutils.py
pesto.egg-info/PKG-INFO
pesto.egg-info/SOURCES.txt
pesto.egg-info/dependency_links.txt
pesto.egg-info/not-zip-safe
pesto.egg-info/requires.txt
pesto.egg-info/top_level.txt
pesto/session/__init__.py
pesto/session/base.py
pesto/session/filesessionmanager.py
pesto/session/memorysessionmanager.py